Metadata-Version: 1.1
Name: basic-calculator-finite
Version: 0.0.1
Summary: Calculator
Home-page: UNKNOWN
Author: Suraj
Author-email: hrishabhsuraj52@gmail.com
License: MIT
Keywords: calculator
Platform: UNKNOWN
Classifier: Development Status :: 5 - Production/Stable
Classifier: Intended Audience :: Education
Classifier: Operating System :: Microsoft :: Windows :: Windows 10
Classifier: License :: OSI Approved :: MIT License
Classifier: Programming Language :: Python :: 3
